testpkg6_ftcao/__init__.py
testpkg6_ftcao/testpkg6_ftcao.py
testpkg6_ftcao-0.1.0.dist-info/LICENSE
testpkg6_ftcao-0.1.0.dist-info/METADATA
testpkg6_ftcao-0.1.0.dist-info/WHEEL
testpkg6_ftcao-0.1.0.dist-info/RECORD
