Metadata-Version: 2.1
Name: testpkg6_ftcao
Version: 0.1.0
Summary: Testing package in clean environment
License: MIT
Author: Frank Cao
Requires-Python: >=3.12.2,<4.0.0
Classifier: License :: OSI Approved :: MIT License
Classifier: Programming Language :: Python :: 3
